SparkAutoML/__init__.py
SparkAutoML/data_module/__init__.py
SparkAutoML/ml_module/__init__.py
SparkAutoML/ml_module/BinaryClassifier_module/__init__.py
SparkAutoML/ml_module/BinaryClassifier_module/classifier_file.py
SparkAutoML/ml_module/Regression_module/__init__.py
SparkAutoML/ml_module/Regression_module/regression_file.py
SparkAutoML/ml_module/preprocessing_module/__init__.py
SparkAutoML/ml_module/preprocessing_module/custom_transformers_file.py
SparkAutoML/ml_module/preprocessing_module/preprocess_file.py
SparkAutoML/utils/BClassifier_evaluator_file.py
SparkAutoML/utils/Regression_evaluator_file.py
SparkAutoML/utils/__init__.py
SparkAutoML/utils/logger_file.py
SparkAutoML/utils/models_dict_file.py
tests/__init__.py
tests/BinaryClassifier/__init__.py
tests/BinaryClassifier/test_BinaryClassifier.py
tests/Regression/__init__.py
tests/Regression/test_Regression.py
tests/preprocessing/__init__.py
tests/preprocessing/test_pipe_categorical_only.py
tests/preprocessing/test_pipe_mixed_types.py
tests/preprocessing/test_pipe_numeric_only.py
SparkAutoML-0.0.15.dist-info/LICENSE
SparkAutoML-0.0.15.dist-info/METADATA
SparkAutoML-0.0.15.dist-info/WHEEL
SparkAutoML-0.0.15.dist-info/top_level.txt
SparkAutoML-0.0.15.dist-info/RECORD
