Metadata-Version: 2.1
Name: SparkAutoML
Version: 0.0.15
Summary: For an easy implementation of spark's machine learning library
Author: Fahad Akbar
Author-email: <fahadakbar@gmail.com>
License: UNKNOWN
Keywords: python,spark,machine learning
Platform: UNKNOWN
Classifier: Development Status :: 1 - Planning
Classifier: Intended Audience :: Developers
Classifier: Programming Language :: Python :: 3.8
Classifier: Operating System :: Unix
Classifier: Operating System :: MacOS :: MacOS X
Classifier: Operating System :: Microsoft :: Windows
License-File: LICENSE
Requires-Dist: pandas
Requires-Dist: numpy
Requires-Dist: pyspark (>=3.2.1)
Requires-Dist: pytest
